blockchain_parser/__init__.py
blockchain_parser/address.py
blockchain_parser/block.py
blockchain_parser/block_header.py
blockchain_parser/blockchain.py
blockchain_parser/index.py
blockchain_parser/input.py
blockchain_parser/output.py
blockchain_parser/script.py
blockchain_parser/transaction.py
blockchain_parser/utils.py
blockchain_parser/tests/__init__.py
blockchain_parser/tests/test_address.py
blockchain_parser/tests/test_block.py
blockchain_parser/tests/test_index.py
blockchain_parser/tests/test_output.py
blockchain_parser/tests/test_script.py
blockchain_parser/tests/test_transaction.py
blockchain_parser/tests/test_utils.py
blockchain_parser/tests/utils.py
blockchain_parser-0.1.6.dist-info/LICENSE
blockchain_parser-0.1.6.dist-info/METADATA
blockchain_parser-0.1.6.dist-info/WHEEL
blockchain_parser-0.1.6.dist-info/top_level.txt
blockchain_parser-0.1.6.dist-info/RECORD
