Metadata-Version: 2.1
Name: blockchain-parser
Version: 0.1.6
Summary: Bitcoin blockchain parser
Home-page: https://github.com/alecalve/python-bitcoin-blockchain-parser
Author: Antoine Le Calvez
Author-email: antoine@p2sh.info
Classifier: Development Status :: 5 - Production/Stable
Classifier: Environment :: Console
Classifier: Intended Audience :: Developers
Classifier: License :: OSI Approved :: GNU Lesser General Public License v3 (LGPLv3)
Classifier: Topic :: Software Development :: Libraries
License-File: LICENSE
Requires-Dist: python-bitcoinlib (==0.11.0)
Requires-Dist: plyvel (==1.5.1)
Requires-Dist: ripemd-hash (==1.0.1)
